api/__init__.py
api/gpt.py
gpt_api-0.2.2.dist-info/METADATA
gpt_api-0.2.2.dist-info/WHEEL
gpt_api-0.2.2.dist-info/top_level.txt
gpt_api-0.2.2.dist-info/RECORD
