Metadata-Version: 2.1
Name: gpt-api
Version: 0.2.2
Summary: gpt api engine
Home-page: UNKNOWN
Author: gpt-api
Author-email: 455255111@qq.com
License: UNKNOWN
Platform: UNKNOWN
Classifier: Intended Audience :: Developers
Classifier: License :: OSI Approved :: MIT License
Classifier: Programming Language :: Python :: 3.9
Requires-Python: >=3.7.0
Requires-Dist: openai
